blendify/__init__.py
blendify/scene.py
blendify/cameras/__init__.py
blendify/cameras/base.py
blendify/cameras/common.py
blendify/colors/__init__.py
blendify/colors/base.py
blendify/colors/common.py
blendify/colors/texture.py
blendify/internal/__init__.py
blendify/internal/execution_decorator.py
blendify/internal/io.py
blendify/internal/parser.py
blendify/internal/positionable.py
blendify/internal/singleton.py
blendify/internal/texture.py
blendify/internal/types.py
blendify/lights/__init__.py
blendify/lights/area.py
blendify/lights/base.py
blendify/lights/collection.py
blendify/lights/common.py
blendify/materials/__init__.py
blendify/materials/base.py
blendify/materials/bsdf.py
blendify/materials/metal.py
blendify/materials/plastic.py
blendify/materials/wireframe.py
blendify/renderables/__init__.py
blendify/renderables/base.py
blendify/renderables/collection.py
blendify/renderables/mesh.py
blendify/renderables/pointcloud.py
blendify/renderables/primitives.py
blendify/utils/__init__.py
blendify/utils/camera_trajectory.py
blendify/utils/image.py
blendify/utils/pointcloud.py
blendify/utils/shadow_catcher.py
blendify/utils/smpl_wrapper.py
blendify-2.1.0.dist-info/licenses/LICENSE
docs/conf.py
docs/pip_readme.md
examples/01_cornell_box.py
examples/02_color_albedo_depth.py
examples/03_mesh_with_texture.py
examples/04_camera_colored_point_cloud.py
examples/05_smpl_movement.py
examples/06_nurbs_trajectory.py
examples/07_materials_and_shadow_catcher.py
examples/08_per_face_material.py
blendify-2.1.0.dist-info/METADATA
blendify-2.1.0.dist-info/WHEEL
blendify-2.1.0.dist-info/top_level.txt
blendify-2.1.0.dist-info/RECORD
