Metadata-Version: 2.4
Name: blendify
Version: 2.1.0
Summary: Python rendering framework for Blender
Author-email: Vladimir Guzov <vguzov@mpi-inf.mpg.de>, Ilya Petrov <ptrvilya@gmail.com>
License:                     GNU GENERAL PUBLIC LICENSE
Project-URL: Homepage, https://github.com/ptrvilya/blendify
Keywords: rendering,pointcloud,blender,mesh
Classifier: Intended Audience :: Developers
Classifier: License :: OSI Approved :: GNU General Public License v3 or later (GPLv3+)
Classifier: Natural Language :: English
Classifier: Operating System :: Unix
Classifier: Programming Language :: Python
Classifier: Programming Language :: Python :: 3
Requires-Python: <3.12,>=3.11
License-File: LICENSE
Requires-Dist: numpy
Requires-Dist: scipy
Requires-Dist: bpy<4.6,>4.5
Requires-Dist: opencv-python-headless
Provides-Extra: docs
Requires-Dist: sphinx; extra == "docs"
Requires-Dist: sphinx-autobuild; extra == "docs"
Requires-Dist: myst_parser; extra == "docs"
Requires-Dist: furo; extra == "docs"
Provides-Extra: utils
Requires-Dist: loguru; extra == "utils"
Requires-Dist: scikit-learn; extra == "utils"
Requires-Dist: open3d; extra == "utils"
Requires-Dist: smplx; extra == "utils"
Requires-Dist: torch; extra == "utils"
Provides-Extra: examples
Requires-Dist: loguru; extra == "examples"
Requires-Dist: scikit-learn; extra == "examples"
Requires-Dist: open3d; extra == "examples"
Requires-Dist: smplx; extra == "examples"
Requires-Dist: torch; extra == "examples"
Requires-Dist: videoio; extra == "examples"
Requires-Dist: scikit-image; extra == "examples"
Requires-Dist: trimesh; extra == "examples"
Provides-Extra: all
Requires-Dist: numpy; extra == "all"
Requires-Dist: scipy; extra == "all"
Requires-Dist: bpy==4.5.2; extra == "all"
Requires-Dist: opencv-python-headless; extra == "all"
Requires-Dist: loguru; extra == "all"
Requires-Dist: scikit-learn; extra == "all"
Requires-Dist: open3d; extra == "all"
Requires-Dist: smplx; extra == "all"
Requires-Dist: torch; extra == "all"
Requires-Dist: videoio; extra == "all"
Requires-Dist: scikit-image; extra == "all"
Requires-Dist: trimesh; extra == "all"
Requires-Dist: sphinx; extra == "all"
Requires-Dist: sphinx-autobuild; extra == "all"
Requires-Dist: myst_parser; extra == "all"
Requires-Dist: furo; extra == "all"
Dynamic: license-file
